odoo/addons/sale_commission_delegated_partner/README.rst
odoo/addons/sale_commission_delegated_partner/__init__.py
odoo/addons/sale_commission_delegated_partner/__manifest__.py
odoo/addons/sale_commission_delegated_partner/i18n/es.po
odoo/addons/sale_commission_delegated_partner/i18n/pt.po
odoo/addons/sale_commission_delegated_partner/i18n/pt_BR.po
odoo/addons/sale_commission_delegated_partner/i18n/sale_commission_delegated_partner.pot
odoo/addons/sale_commission_delegated_partner/models/__init__.py
odoo/addons/sale_commission_delegated_partner/models/res_partner.py
odoo/addons/sale_commission_delegated_partner/models/sale_commission_settlement.py
odoo/addons/sale_commission_delegated_partner/readme/CONFIGURE.rst
odoo/addons/sale_commission_delegated_partner/readme/CONTRIBUTORS.rst
odoo/addons/sale_commission_delegated_partner/readme/DESCRIPTION.rst
odoo/addons/sale_commission_delegated_partner/static/description/icon.png
odoo/addons/sale_commission_delegated_partner/static/description/index.html
odoo/addons/sale_commission_delegated_partner/tests/__init__.py
odoo/addons/sale_commission_delegated_partner/tests/test_sale_commission_delegate_partner.py
odoo/addons/sale_commission_delegated_partner/views/res_partner.xml
odoo14_addon_sale_commission_delegated_partner-14.0.1.0.1.dist-info/METADATA
odoo14_addon_sale_commission_delegated_partner-14.0.1.0.1.dist-info/WHEEL
odoo14_addon_sale_commission_delegated_partner-14.0.1.0.1.dist-info/top_level.txt
odoo14_addon_sale_commission_delegated_partner-14.0.1.0.1.dist-info/RECORD
